pmorm/__init__.py
pmorm/mysql.py
Pmorm-0.21.dist-info/LICENSE
Pmorm-0.21.dist-info/METADATA
Pmorm-0.21.dist-info/WHEEL
Pmorm-0.21.dist-info/top_level.txt
Pmorm-0.21.dist-info/RECORD
